COPYING
MANIFEST.in
README.md
conftest.py
dev-requirements.txt
pytest.ini
requirements.txt
run-dev-server.py
setup.py
tox.ini
conf/settings.py.example
conf/policies/fedora.yaml
conf/policies/redhat.yaml
docs/Makefile
docs/api.rst
docs/conf.py
docs/dev-guide.rst
docs/docker-compose.rst
docs/index.rst
docs/package-specific-policies.rst
docs/policies.rst
docs/python-intersphinx.inv
docs/release-notes.rst
docs/todo.rst
docs/_build/html/objects.inv
fedmsg.d/config.py
fedmsg.d/resultsdb.py
fedmsg.d/waiverdb.py
greenwave/__init__.py
greenwave/api_v1.py
greenwave/app_factory.py
greenwave/cache.py
greenwave/config.py
greenwave/logger.py
greenwave/policies.py
greenwave/resources.py
greenwave/safe_yaml.py
greenwave/utils.py
greenwave/wsgi.py
greenwave.egg-info/PKG-INFO
greenwave.egg-info/SOURCES.txt
greenwave.egg-info/dependency_links.txt
greenwave.egg-info/entry_points.txt
greenwave.egg-info/not-zip-safe
greenwave.egg-info/requires.txt
greenwave.egg-info/top_level.txt
greenwave/consumers/__init__.py
greenwave/consumers/resultsdb.py
greenwave/consumers/waiverdb.py
greenwave/tests/__init__.py
greenwave/tests/test_policies.py
greenwave/tests/test_resultsdb_consumer.py
greenwave/tests/test_summary.py
greenwave/tests/test_utils.py