Metadata-Version: 1.2
Name: greenwave
Version: 0.9.4
Summary: Greenwave is a service to decide whether a software artifact can pass certain gating points in a software delivery pipeline
Home-page: https://pagure.io/greenwave/
Maintainer: Fedora Infrastructure Team
Maintainer-email: infrastructure@lists.fedoraproject.org
License: GPLv2+
Platform: Fedora
Platform: GNU/Linux
Classifier: Development Status :: 1 - Planning
Classifier: Framework :: Flask
Classifier: License :: OSI Approved :: GNU General Public License v2 or later (GPLv2+)
Classifier: Operating System :: POSIX :: Linux
Classifier: Programming Language :: Python :: 3
Classifier: Programming Language :: Python :: 3.4
Classifier: Programming Language :: Python :: 3.5
Classifier: Programming Language :: Python :: 3.6
